vss_communication/__init__.py
vss_communication/classes.py
vss_communication/command_pb2.py
vss_communication-0.0.1.dist-info/METADATA
vss_communication-0.0.1.dist-info/WHEEL
vss_communication-0.0.1.dist-info/top_level.txt
vss_communication-0.0.1.dist-info/RECORD
